tool.py
coinbase_agentkit_alith-0.2.0.dist-info/METADATA
coinbase_agentkit_alith-0.2.0.dist-info/WHEEL
coinbase_agentkit_alith-0.2.0.dist-info/top_level.txt
coinbase_agentkit_alith-0.2.0.dist-info/RECORD
