Metadata-Version: 2.2
Name: coinbase-agentkit-alith
Version: 0.2.0
Summary: Coinbase Agentkit Alith Python Integration
License: Apache-2.0
Requires-Python: >=3.7
Requires-Dist: alith>=0.4.2
Requires-Dist: coinbase-agentkit>=0.1.6
